{
  "heading": "Packer Overview",
  "subheading": "Use Packer to automatically create machine images for multiple platforms.",
  "blocks": [
    {
      "type": "heading",
      "level": 2,
      "size": 400,
      "heading": "Explore Packer Documentation"
    },
    {
      "type": "get_started",
      "product": "packer",
      "heading": "Introduction to Packer",
      "text": "Packer is controlled using a command-line interface. All interaction with Packer is done via the packer tool.",
      "link": {
        "text": "Learn more",
        "url": "https://learn.hashicorp.com/tutorials/packer/get-started-install-cli"
      }
    },
    {
      "type": "cards",
      "columns": 2,
      "cards": [
        {
          "icon": "IconDocs",
          "heading": "Packer Reference Documentation",
          "text": "Lorem ipsum dolor sit amet, consectetur adipiscing elit. Dui elementum sit at mauris. Integer diam vestibulum egestas diam euismod ornare auctor.",
          "url": "/packer/docs"
        },
        {
          "icon": "IconTerminal",
          "heading": "Packer CLI",
          "text": "Lorem ipsum dolor sit amet, consectetur adipiscing elit. Dui elementum sit at mauris. Integer diam vestibulum egestas diam euismod ornare auctor.",
          "url": "/packer/docs/commands"
        },
        {
          "icon": "IconServer",
          "heading": "Packer API",
          "text": "Lorem ipsum dolor sit amet, consectetur adipiscing elit. At sit ultricies sed bibendum lectus montes.",
          "url": "https://cloud.hashicorp.com/api-docs/packer"
        },
        {
          "icon": "IconDownload",
          "heading": "Packer Install",
          "text": "Lorem ipsum dolor sit amet, consectetur adipiscing elit. Cursus donec rutrum dignissim et in at mattis.",
          "url": "/packer/downloads"
        }
      ]
    },
    {
      "type": "heading",
      "level": 2,
      "heading": "Featured Packer Documentation",
      "size": 300
    },
    {
      "type": "cards",
      "columns": 3,
      "cards": [
        {
          "heading": "Morbi nam convallis.",
          "text": "Lorem ipsum dolor sit amet, consectetur adipiscing elit. Nisl in eu est ut vulputate neque.",
          "url": "/packer"
        },
        {
          "heading": "Diam tellus egestas lacus.",
          "text": "Lorem ipsum dolor sit amet, consectetur adipiscing elit. Congue a ut a amet gravida.",
          "url": "/packer"
        },
        {
          "heading": "Sed penatibus nulla.",
          "text": "Lorem ipsum dolor sit amet, consectetur adipiscing elit. Justo ipsum sagittis laoreet vel.",
          "url": "/packer"
        }
      ]
    },
    {
      "type": "heading",
      "level": 2,
      "heading": "Lorem ipsum dolor sit amet",
      "size": 300
    },
    {
      "type": "cards",
      "columns": 3,
      "cards": [
        {
          "heading": "Etiam quis in ac non quam.",
          "text": "Lorem ipsum dolor sit amet, consectetur adipiscing elit. Ultricies nisi interdum vitae id.",
          "url": "/packer"
        },
        {
          "heading": "Aliquet eu risus dis sed.",
          "text": "Lorem ipsum dolor sit amet, consectetur adipiscing elit. Sit neque mattis phasellus quam.",
          "url": "/packer"
        },
        {
          "heading": "Ornare faucibus blandit id.",
          "text": "Lorem ipsum dolor sit amet, consectetur adipiscing elit. Urna donec gravida viverra.",
          "url": "/packer"
        }
      ]
    },
    {
      "type": "heading",
      "level": 2,
      "heading": "Lorem ipsum dolor sit amet",
      "size": 300
    },
    {
      "type": "cards",
      "columns": 3,
      "cards": [
        {
          "heading": "Interdum sollicitudin.",
          "text": "Lorem ipsum dolor sit amet, consectetur adipiscing elit. Sed elementum lectus posuere.",
          "url": "/packer"
        },
        {
          "heading": "Ornare nibh semper.",
          "text": "Lorem ipsum dolor sit amet, consectetur adipiscing elit. Ut commodo facilisis diam.",
          "url": "/packer"
        },
        {
          "heading": "Fames nibh gravida.",
          "text": "Lorem ipsum dolor sit amet, consectetur adipiscing elit.",
          "url": "/packer"
        }
      ]
    },
    {
      "type": "heading",
      "level": 2,
      "heading": "Start Learning",
      "size": 300
    },
    {
      "type": "cards",
      "columns": 2,
      "cards": [
        {
          "heading": "Vitae aliquam nisl ligula pharetra.",
          "text": "Lorem ipsum dolor sit amet, consectetur adipiscing elit. Eget eget velit nibh odio a blandit leo euismod.",
          "url": "https://learn.hashicorp.com/packer",
          "tags": ["packer"]
        },
        {
          "heading": "Dapibus elementum pretium rutrum odio.",
          "text": "Lorem ipsum dolor sit amet, consectetur adipiscing elit. Praesent sit enim, risus duis. Lectus vitae.",
          "url": "https://learn.hashicorp.com/packer",
          "tags": ["packer"]
        },
        {
          "heading": "Eu magna mattis ultricies aliquet gravida.",
          "text": "Lorem ipsum dolor sit amet, consectetur adipiscing elit. Egestas massa eget amet lectus turpis sapien.",
          "url": "https://learn.hashicorp.com/packer",
          "tags": ["packer"]
        },
        {
          "heading": "Senectus rhoncus quam ullamcorper vel.",
          "text": "Lorem ipsum dolor sit amet, consectetur adipiscing elit. Donec semper facilisis a ultrices turpis id proin.",
          "url": "https://learn.hashicorp.com/packer",
          "tags": ["packer"]
        }
      ]
    }
  ]
}
